Metadata-Version: 2.1
Name: pingpkg
Version: 0.0.1
Summary: Used to ping network devices
Home-page: https://pypi.org/project/pingpkg/
Author: xizhao_li
Author-email: hard_rock_l@163.com
Classifier: Programming Language :: Python :: 3
Classifier: License :: OSI Approved :: MIT License
Classifier: Operating System :: OS Independent
Requires-Python: >=3.6
Requires-Dist: openpyxl
